vec_geohash/__init__.py
vec_geohash/_version.py
vec_geohash/vec_geohash.py
vec_geohash-0.0.3.dist-info/LICENSE.txt
vec_geohash-0.0.3.dist-info/METADATA
vec_geohash-0.0.3.dist-info/WHEEL
vec_geohash-0.0.3.dist-info/top_level.txt
vec_geohash-0.0.3.dist-info/RECORD
