Metadata-Version: 2.1
Name: vec-geohash
Version: 0.0.3
Summary: Vectorized functions for transforming latitude and longitude coordinates to Map Tile coordinates, Map Pixel coordinates or QuadKeys
Author-email: Filip Jakovljevic <fillix96@gmail.com>
License: The MIT License (MIT)
Project-URL: homepage, https://github.com/FJakovljevic/vec_geohash
Keywords: quadkeys,tiles,gis,geohash,geohash gis,geo tiles,map tile system
Classifier: Programming Language :: Python :: 3
Classifier: Programming Language :: Python :: 3.7
Classifier: Programming Language :: Python :: 3.8
Classifier: Programming Language :: Python :: 3.9
Classifier: Programming Language :: Python :: 3.10
Classifier: Programming Language :: Python :: 3.11
Requires-Python: >=3.7
License-File: LICENSE.txt
Requires-Dist: numpy
Requires-Dist: importlib-metadata ; python_version < "3.8"
